koreanWikiExtractor/__init__.py
koreanWikiExtractor/text_processor.py
koreanWikiExtractor_test2-0.1.dist-info/METADATA
koreanWikiExtractor_test2-0.1.dist-info/WHEEL
koreanWikiExtractor_test2-0.1.dist-info/top_level.txt
koreanWikiExtractor_test2-0.1.dist-info/RECORD
