Metadata-Version: 2.1
Name: koreanWikiExtractor-test2
Version: 0.1
Summary: convert MediaWiki to plain text
Home-page: https://github.com/Kim-Jaehun/Korean-WikiExtractor
Author: Kim Jaehun
Author-email: wogjs217@gmail.com
License: MIT
Platform: UNKNOWN
Classifier: Programming Language :: Python :: 3.6
